{"CASHCAT": {"sens": "reversion", "confiance": 0.35, "raison": "Listing Hyperliquid perps (3x) + Solana expansion + whale buys ($233k Ansem). Mais: momentum-driven meme peak typique (ATH $0.211 le 11 juil), liquidation cascade 60% perps, thin l", "ts": "2026-07-14T22:12:30.913284Z", "move_pct": 12.86}, "LIT": {"sens": "reversion", "confiance": 0.55, "raison": "Rallye +11.3% sur catalyseurs anciens (tokenomics burn 11 Jul, Robinhood intégr. 10 Jul). RSI 78+ (suracheté), bearish divergence détectée. Momentum déjà 60%↑ en 7j.", "ts": "2026-07-14T22:12:30.913284Z", "move_pct": 11.26}, "ZEC": {"sens": "momentum", "confiance": 0.72, "raison": "Ironwood upgrade formal verification progress + July 28 mainnet activation catalyst restoring trust post-vulnerability. Short liquidations $7.6M+. OI spike 22%, funding positive.", "ts": "2026-07-14T22:12:30.913284Z", "move_pct": 10.6}, "SPX": {"sens": "reversion", "confiance": 0.35, "raison": "CPI faible catalyse tech, mais +10.3% sur SPX perp diverge réalité; risque correction moyen-terme.", "ts": "2026-07-14T23:12:33.261012Z", "move_pct": 10.26}, "MET": {"sens": "reversion", "confiance": 0.35, "raison": "Aucun catalyseur clair identifié. MET historiquement en baisse prolongée (-90% ATH). Probable pullback technique ou squeeze court terme sans news support.", "ts": "2026-07-15T03:34:50.639097Z", "move_pct": 12.17}, "PUMP": {"sens": "reversion", "confiance": 0.55, "raison": "Pump.fun acquis trading terminal (10% surge); mais unlock 82.5B tokens 12-Jul (~29.23% circulating) crée sell pressure contraire. Rally dérivé de meme momentum + buybacks ($3.7M/wk", "ts": "2026-07-15T03:34:50.639097Z", "move_pct": 10.29}, "0G": {"sens": "reversion", "confiance": 0.25, "raison": "Pas de catalyseur macro identifié; move H1 2026 update mineur. Données actuelles montrent -2.9% 24h, non +13.3%.", "ts": "2026-07-15T15:50:22.636896Z", "move_pct": 13.31}, "ETHFI": {"sens": "reversion", "confiance": 0.45, "raison": "Macro ETH relief rally + LRT sentiment spike. No ETHFI-specific catalyst. Recent +25% rallies retracted. Mixed technicals, large long liquidations. Short-term relief bounce likely ", "ts": "2026-07-15T19:55:21.442326Z", "move_pct": 12.14}, "ONDO": {"sens": "reversion", "confiance": 0.35, "raison": "Aucun catalyseur clair identifié (pas listing, hack, déblocage, announce maj). Move 15.3% surprenant sans news fondamentale à 2026-07-15.", "ts": "2026-07-15T21:10:39.892347Z", "move_pct": 15.26}}