{"HMSTR": {"sens": "reversion", "confiance": 0.38, "raison": "Pas de catalyseur unique net: dump apres pump +88% en 7j (cycle high 0.000425 depuis ATL 0.000126). RSI oversold ~29, sentiment F&G 24. Micro-cap ~20M$, rebond technique probable", "ts": "2026-07-08T00:11:25.229118Z", "move_pct": -32.19}, "VINE": {"sens": "reversion", "confiance": 0.38, "raison": "Pas de catalyseur dur (hack/listing/unlock). Move = memecoin illiquide (MC~10M), sell-off retail vs whales acheteurs, CMF negatif. Techniques baissiers mais rebond-de-panique proba", "ts": "2026-07-08T00:11:25.229118Z", "move_pct": -18.16}, "LDO": {"sens": "reversion", "confiance": 0.4, "raison": "Pas de catalyseur ponctuel net sur 24h: seulement narratif buyback NEST/Staking Router v3 deja connu + rebond ~20% depuis ATL. Sentiment Fear&Greed 13, MA baissieres. Move pousse.", "ts": "2026-07-08T00:11:25.229118Z", "move_pct": 11.16}, "XPL": {"sens": "momentum", "confiance": 0.55, "raison": "Overhang unlock ~1B XPL le 28/07 (fin lock-up public sale US); book HIP-3 tres fin amplifie les moves. Deja -94% ATH, tendance macro baissiere. Reversion technique possible mais di", "ts": "2026-07-08T00:11:25.229118Z", "move_pct": -10.48}, "JTO": {"sens": "reversion", "confiance": 0.55, "raison": "Unlock JTO ~$8-14M etale sur 6-12 juil + pression concurrentielle Flowra sur dominance validateur; pas de hack. Dilution absorbee + catalyseur JTX/JTX juillet = rebond probable apr", "ts": "2026-07-08T09:08:56.265166Z", "move_pct": -21.66}, "PUMP": {"sens": "reversion", "confiance": 0.55, "raison": "Baisse liee au FUD sur unlock PUMP (~130M$, semaine 2 juillet 2026). Mais buyback/burn 3.7M$ actif, shorts>longs liquides (295M vs 232M), sentiment social bullish: rebond probable.", "ts": "2026-07-08T09:08:56.265166Z", "move_pct": -11.23}}