{"POPCAT": {"ouvert": false}, "FARTCOIN": {"ouvert": false}, "SPX": {"ouvert": false}, "S": {"ouvert": false}, "XPL": {"ouvert": false}, "WLD": {"ouvert": false}, "ETHFI": {"ouvert": false}, "ADA": {"ouvert": false}, "GRASS": {"ouvert": true, "side": 1, "entry": 0.49036, "ts": "2026-07-06T10:56:28.770155+00:00", "mode": "REV", "source": "ia_piece"}, "KPEPE": {"ouvert": false}, "KBONK": {"ouvert": false}, "HMSTR": {"ouvert": false}, "MEGA": {"ouvert": false}, "VVV": {"ouvert": false}, "LIT": {"ouvert": true, "side": -1, "entry": 2.4316, "ts": "2026-07-05T15:47:27.179626+00:00", "mode": "REV", "source": "ia_piece"}, "AERO": {"ouvert": false}, "EIGEN": {"ouvert": false}, "TRB": {"ouvert": true, "side": 1, "entry": 18.211, "ts": "2026-07-06T05:58:01.488898+00:00", "mode": "MOM", "source": "tendance_piece"}, "PYTH": {"ouvert": true, "side": 1, "entry": 0.044105, "ts": "2026-07-06T10:56:28.770155+00:00", "mode": "MOM", "source": "tendance_piece"}, "MON": {"ouvert": true, "side": 1, "entry": 0.022715, "ts": "2026-07-06T10:56:28.770155+00:00", "mode": "MOM", "source": "tendance_piece"}}